tacker_horizon-12.0.0-py3.8-nspkg.pth
tacker_horizon/enabled/_80_nfv.py
tacker_horizon/enabled/__init__.py
tacker_horizon/openstack_dashboard/__init__.py
tacker_horizon/openstack_dashboard/api/__init__.py
tacker_horizon/openstack_dashboard/api/tacker.py
tacker_horizon/openstack_dashboard/dashboards/__init__.py
tacker_horizon/openstack_dashboard/dashboards/nfv/__init__.py
tacker_horizon/openstack_dashboard/dashboards/nfv/dashboard.py
tacker_horizon/openstack_dashboard/dashboards/nfv/utils.py
tacker_horizon/openstack_dashboard/dashboards/nfv/lccnsubscription/__init__.py
tacker_horizon/openstack_dashboard/dashboards/nfv/lccnsubscription/forms.py
tacker_horizon/openstack_dashboard/dashboards/nfv/lccnsubscription/panel.py
tacker_horizon/openstack_dashboard/dashboards/nfv/lccnsubscription/tables.py
tacker_horizon/openstack_dashboard/dashboards/nfv/lccnsubscription/tabs.py
tacker_horizon/openstack_dashboard/dashboards/nfv/lccnsubscription/urls.py
tacker_horizon/openstack_dashboard/dashboards/nfv/lccnsubscription/views.py
tacker_horizon/openstack_dashboard/dashboards/nfv/lccnsubscription/templates/lccnsubscription/_create_lccn_subscription.html
tacker_horizon/openstack_dashboard/dashboards/nfv/lccnsubscription/templates/lccnsubscription/create_lccn_subscription.html
tacker_horizon/openstack_dashboard/dashboards/nfv/lccnsubscription/templates/lccnsubscription/detail.html
tacker_horizon/openstack_dashboard/dashboards/nfv/lccnsubscription/templates/lccnsubscription/index.html
tacker_horizon/openstack_dashboard/dashboards/nfv/lccnsubscription/templates/lccnsubscription/lccnsubsc_detail.html
tacker_horizon/openstack_dashboard/dashboards/nfv/nscatalog/__init__.py
tacker_horizon/openstack_dashboard/dashboards/nfv/nscatalog/forms.py
tacker_horizon/openstack_dashboard/dashboards/nfv/nscatalog/panel.py
tacker_horizon/openstack_dashboard/dashboards/nfv/nscatalog/tables.py
tacker_horizon/openstack_dashboard/dashboards/nfv/nscatalog/tabs.py
tacker_horizon-12.0.0.dist-info/AUTHORS
tacker_horizon-12.0.0.dist-info/LICENSE
tacker_horizon-12.0.0.dist-info/METADATA
tacker_horizon-12.0.0.dist-info/WHEEL
tacker_horizon-12.0.0.dist-info/namespace_packages.txt
tacker_horizon-12.0.0.dist-info/pbr.json
tacker_horizon-12.0.0.dist-info/top_level.txt
tacker_horizon-12.0.0.dist-info/RECORD
