Metadata-Version: 2.1
Name: tacker-horizon
Version: 12.0.0
Summary: Tacker extension for Horizon
Home-page: https://docs.openstack.org/tacker-horizon/latest/
Author: OpenStack
Author-email: openstack-discuss@lists.openstack.org
Classifier: Environment :: OpenStack
Classifier: Intended Audience :: Developers
Classifier: Intended Audience :: Information Technology
Classifier: Intended Audience :: System Administrators
Classifier: License :: OSI Approved :: Apache Software License
Classifier: Operating System :: POSIX :: Linux
Classifier: Programming Language :: Python
Classifier: Programming Language :: Python :: 3
Classifier: Programming Language :: Python :: 3.6
Classifier: Programming Language :: Python :: 3.7
Classifier: Programming Language :: Python :: 3.8
Classifier: Programming Language :: Python :: 3.9
Classifier: Programming Language :: Python :: 3.10
License-File: LICENSE
License-File: AUTHORS
Requires-Dist: Django >=4.2.23
Requires-Dist: oslo.log >=7.2.0
Requires-Dist: oslo.serialization >=5.7.0
Requires-Dist: pbr >=6.0.0
Requires-Dist: python-tackerclient >=2.3.0
Requires-Dist: horizon >=25.4.0
